erk_sh_bootstrap/__init__.py
erk_sh_bootstrap/cli.py
erk_sh_bootstrap-1.0.0.dist-info/METADATA
erk_sh_bootstrap-1.0.0.dist-info/WHEEL
erk_sh_bootstrap-1.0.0.dist-info/entry_points.txt
erk_sh_bootstrap-1.0.0.dist-info/RECORD
