Metadata-Version: 2.4
Name: erk-sh-bootstrap
Version: 1.0.0
Summary: Thin bootstrap that delegates to project-local erk
Requires-Python: >=3.10
